RCBS/__init__.py
RCBS/_version.py
RCBS/exceptions.py
RCBS/snippets.py
RCBS/md_analyser/__init__.py
RCBS/md_analyser/frame_extractor.py
RCBS/md_analyser/measurements.py
RCBS/md_analyser/selections.py
RCBS.py-0.0.1.dist-info/LICENSE
RCBS.py-0.0.1.dist-info/METADATA
RCBS.py-0.0.1.dist-info/WHEEL
RCBS.py-0.0.1.dist-info/top_level.txt
RCBS.py-0.0.1.dist-info/RECORD
