Metadata-Version: 2.1
Name: RCBS.py
Version: 0.0.1
Summary: Python package useful for analysing MD trajectories and creating QM/MM models built on top of MDAnalysis. All MD formats compatible with MDAnalysis are compatible with RCBS, while QM/MM capacities are compatible with ChemShell. The aim of this package is to develop an easy-to-use way to analyse MD trajectories, while keeping a good performance.
Home-page: https://github.com/dynamicsUAB/RCBS.py
Download-URL: https://github.com/dynamicsUAB/RCBS.py
Author: Miquel Canyelles Niño
License: UNKNOWN
Keywords: biochemistry,simulations,MDAnalysis,molecular dynamics
Platform: UNKNOWN
License-File: LICENSE
Requires-Dist: numpy
Requires-Dist: pyyaml
Requires-Dist: MDAnalysis
